DBTunnelBridge/__init__.py
DBTunnelBridge/db_connection.py
DBTunnelBridge/ssh_tunnel.py
dbtunnelbridge-0.0.1.dist-info/METADATA
dbtunnelbridge-0.0.1.dist-info/WHEEL
dbtunnelbridge-0.0.1.dist-info/licenses/LICENSE
dbtunnelbridge-0.0.1.dist-info/RECORD
