Metadata-Version: 2.4
Name: DBTunnelBridge
Version: 0.0.1
Summary: A package for managing local and remote database connections with optional SSH tunneling.
Project-URL: Homepage, https://github.com/kwilsonmg/DBTunnelBridge
Project-URL: Repository, https://github.com/kwilsonmg/DBTunnelBridge
Author: Kyle Wilson
License-Expression: MIT
License-File: LICENSE
Requires-Python: >=3.11
Requires-Dist: bcrypt>=4.3.0
Requires-Dist: cffi>=1.17.1
Requires-Dist: cryptography>=44.0.2
Requires-Dist: paramiko>=3.5.1
Requires-Dist: pycparser>=2.22
Requires-Dist: pymysql>=1.1.1
Requires-Dist: pynacl>=1.5.0
Requires-Dist: sqlalchemy>=2.0.39
Requires-Dist: sshtunnel>=0.4.0
Requires-Dist: typing-extensions>=4.12.2
